<?xml version="1.0" encoding="ISO-8859-1"?>
<Vehicle>
    <name>Angry Vehicle 3</name>
    <author>Some sweaty angry guys</author>
    <description>This is a very angry little vehicle 3</description>
    <LastModified>25/04/2009 17:38:48</LastModified>
    <max_battery_capacity>100.0</max_battery_capacity>
    <curr_battery_capacity>100.0</curr_battery_capacity>
    <motorStrength>10</motorStrength>
    <aggression>20</aggression>
    <Colour>
        <red>166</red>
        <green>207</green>
        <blue>207</blue>
    </Colour>
    <VehicleComponent>
        <type>LEFT</type>
        <LeftSensorHeat>34</LeftSensorHeat>
        <LeftSensorLight>45</LeftSensorLight>
        <LeftSensorPower>50</LeftSensorPower>
        <LeftSensorWater>50</LeftSensorWater>
    </VehicleComponent>
    <VehicleComponent>
        <type>RIGHT</type>
        <RightSensorHeat>12</RightSensorHeat>
        <RightSensorLight>46</RightSensorLight>
        <RightSensorPower>10</RightSensorPower>
        <RightSensorWater>-8</RightSensorWater>
    </VehicleComponent>
</Vehicle>
